pypigeonhole_dbaccess/__init__.py
pypigeonhole_dbaccess/app_setup.py
pypigeonhole_dbaccess/bulk_uploader.py
pypigeonhole_dbaccess/obj_mapper.py
pypigeonhole_dbaccess/tx_manager.py
pypigeonhole_dbaccess-0.0.1.dist-info/LICENSE.md
pypigeonhole_dbaccess-0.0.1.dist-info/METADATA
pypigeonhole_dbaccess-0.0.1.dist-info/WHEEL
pypigeonhole_dbaccess-0.0.1.dist-info/top_level.txt
pypigeonhole_dbaccess-0.0.1.dist-info/RECORD
