Metadata-Version: 2.1
Name: pypigeonhole-dbaccess
Version: 0.0.1
Summary: Python OR mapping tools
Home-page: https://github.com/psilons/pypigeonhole-dbaccess
Author: psilons
Author-email: psilons.quanta@gmail.com
License: MIT
Platform: UNKNOWN
Requires-Python: >=3.6
Requires-Dist: pyodbc (==4.0.30)
Requires-Dist: pypigeonhole-simple-utils
